[
    
    {
        "key": "ctrl+b z",
        "command": "workbench.action.toggleEditorWidths"
    } ,
    {
        "command": "vscode-neovim.compositeEscape1",
        "key": "j",
        "when": "neovim.mode == insert && editorTextFocus",
        "args": "j"
    },
    {
        "command": "vscode-neovim.compositeEscape2",
        "key": "k",
        "when": "neovim.mode == insert && editorTextFocus",
        "args": "k"
    },
    {
        "key": "ctrl+cmd+r",
        "command": "workbench.action.debug.restart",
        "when": "inDebugMode"
    },
    {
        "key": "shift+cmd+f5",
        "command": "-workbench.action.debug.restart",
        "when": "inDebugMode"
    },
    {
        "key": "ctrl+j",
        "command": "selectNextCodeAction",
        "when": "codeActionMenuVisible"
    },
    {
        "key": "cmd+down",
        "command": "-selectNextCodeAction",
        "when": "codeActionMenuVisible"
    },
    {
        "key": "ctrl+j",
        "command": "selectNextSuggestion",
        "when": "suggestWidgetMultipleSuggestions && suggestWidgetVisible && textInputFocus"
    },
    {
        "key": "down",
        "command": "-selectNextSuggestion",
        "when": "suggestWidgetMultipleSuggestions && suggestWidgetVisible && textInputFocus"
    },
    {
        "key": "cmd+down",
        "command": "-selectNextSuggestion",
        "when": "suggestWidgetMultipleSuggestions && suggestWidgetVisible && textInputFocus"
    },
    {
        "key": "ctrl+k",
        "command": "selectPrevSuggestion",
        "when": "suggestWidgetMultipleSuggestions && suggestWidgetVisible && textInputFocus"
    },
    {
        "key": "up",
        "command": "-selectPrevSuggestion",
        "when": "suggestWidgetMultipleSuggestions && suggestWidgetVisible && textInputFocus"
    },
    {
        "key": "ctrl+j",
        "command": "history.showNext",
        "when": "historyNavigationForwardsEnabled && historyNavigationWidgetFocus && !suggestWidgetVisible"
    },
    {
        "key": "down",
        "command": "-history.showNext",
        "when": "historyNavigationForwardsEnabled && historyNavigationWidgetFocus && !suggestWidgetVisible"
    },
    {
        "key": "ctrl+j",
        "command": "interactive.history.next",
        "when": "!suggestWidgetVisible && resourceScheme == 'vscode-interactive' && interactiveInputCursorAtBoundary != 'none' && interactiveInputCursorAtBoundary != 'top'"
    },
    {
        "key": "down",
        "command": "-interactive.history.next",
        "when": "!suggestWidgetVisible && resourceScheme == 'vscode-interactive' && interactiveInputCursorAtBoundary != 'none' && interactiveInputCursorAtBoundary != 'top'"
    },
    {
        "key": "ctrl+j",
        "command": "list.focusDown",
        "when": "listFocus && !inputFocus"
    },
    {
        "key": "down",
        "command": "-list.focusDown",
        "when": "listFocus && !inputFocus"
    },
    {
        "key": "down",
        "command": "-selectNextCodeAction",
        "when": "codeActionMenuVisible"
    },
    {
        "key": "ctrl+j",
        "command": "settings.action.focusSettingsFile",
        "when": "inSettingsSearch && !suggestWidgetVisible"
    },
    {
        "key": "down",
        "command": "-settings.action.focusSettingsFile",
        "when": "inSettingsSearch && !suggestWidgetVisible"
    },
    {
        "key": "ctrl+j",
        "command": "settings.action.focusSettingsFromSearch",
        "when": "inSettingsSearch && !suggestWidgetVisible"
    },
    {
        "key": "down",
        "command": "-settings.action.focusSettingsFromSearch",
        "when": "inSettingsSearch && !suggestWidgetVisible"
    },
    {
        "key": "ctrl+j",
        "command": "workbench.action.terminal.navigationModeFocusNext",
        "when": "accessibilityModeEnabled && terminalA11yTreeFocus && terminalNavigationModeActive && terminalProcessSupported || accessibilityModeEnabled && terminalFocus && terminalNavigationModeActive && terminalProcessSupported"
    },
    {
        "key": "down",
        "command": "-workbench.action.terminal.navigationModeFocusNext",
        "when": "accessibilityModeEnabled && terminalA11yTreeFocus && terminalNavigationModeActive && terminalProcessSupported || accessibilityModeEnabled && terminalFocus && terminalNavigationModeActive && terminalProcessSupported"
    },
    {
        "key": "ctrl+j",
        "command": "workbench.statusBar.focusNext",
        "when": "statusBarFocused"
    },
    {
        "key": "down",
        "command": "-workbench.statusBar.focusNext",
        "when": "statusBarFocused"
    },
    {
        "key": "ctrl+j",
        "command": "workbench.banner.focusNextAction",
        "when": "bannerFocused"
    },
    {
        "key": "down",
        "command": "-workbench.banner.focusNextAction",
        "when": "bannerFocused"
    },
    {
        "key": "ctrl+j",
        "command": "workbench.action.interactivePlayground.arrowDown",
        "when": "interactivePlaygroundFocus && !editorTextFocus"
    },
    {
        "key": "down",
        "command": "-workbench.action.interactivePlayground.arrowDown",
        "when": "interactivePlaygroundFocus && !editorTextFocus"
    },
    {
        "key": "ctrl+j",
        "command": "showNextParameterHint",
        "when": "editorFocus && parameterHintsMultipleSignatures && parameterHintsVisible"
    },
    {
        "key": "down",
        "command": "-showNextParameterHint",
        "when": "editorFocus && parameterHintsMultipleSignatures && parameterHintsVisible"
    },
    {
        "key": "ctrl+j",
        "command": "scm.viewNextCommit",
        "when": "scmInputIsInLastPosition && scmRepository && !suggestWidgetVisible"
    },
    {
        "key": "down",
        "command": "-scm.viewNextCommit",
        "when": "scmInputIsInLastPosition && scmRepository && !suggestWidgetVisible"
    },
    {
        "key": "ctrl+j",
        "command": "notifications.focusNextToast",
        "when": "notificationFocus && notificationToastsVisible"
    },
    {
        "key": "down",
        "command": "-notifications.focusNextToast",
        "when": "notificationFocus && notificationToastsVisible"
    },
    {
        "key": "down",
        "command": "cursorDown",
        "when": "textInputFocus"
    },
    {
        "key": "down",
        "command": "-cursorDown",
        "when": "textInputFocus"
    },
    {
        "key": "ctrl+j",
        "command": "breadcrumbs.selectFocused",
        "when": "breadcrumbsActive && breadcrumbsVisible"
    },
    {
        "key": "down",
        "command": "-breadcrumbs.selectFocused",
        "when": "breadcrumbsActive && breadcrumbsVisible"
    },
    {
        "key": "ctrl+j",
        "command": "notebook.focusNextEditor",
        "when": "config.notebook.navigation.allowNavigateToSurroundingCells && notebookCursorNavigationMode && notebookEditorFocused && !notebookCellMarkdownEditMode && notebookCellType == 'markup'"
    },
    {
        "key": "down",
        "command": "-notebook.focusNextEditor",
        "when": "config.notebook.navigation.allowNavigateToSurroundingCells && notebookCursorNavigationMode && notebookEditorFocused && !notebookCellMarkdownEditMode && notebookCellType == 'markup'"
    },
    {
        "key": "ctrl+j",
        "command": "notebook.focusNextEditor",
        "when": "config.notebook.navigation.allowNavigateToSurroundingCells && editorTextFocus && inputFocus && notebookEditorFocused && notebookEditorCursorAtBoundary != 'none' && notebookEditorCursorAtBoundary != 'top'"
    },
    {
        "key": "down",
        "command": "-notebook.focusNextEditor",
        "when": "config.notebook.navigation.allowNavigateToSurroundingCells && editorTextFocus && inputFocus && notebookEditorFocused && notebookEditorCursorAtBoundary != 'none' && notebookEditorCursorAtBoundary != 'top'"
    },
    {
        "key": "ctrl+k",
        "command": "workbench.statusBar.focusPrevious",
        "when": "statusBarFocused"
    },
    {
        "key": "up",
        "command": "-workbench.statusBar.focusPrevious",
        "when": "statusBarFocused"
    },
    {
        "key": "ctrl+k",
        "command": "workbench.banner.focusPreviousAction",
        "when": "bannerFocused"
    },
    {
        "key": "up",
        "command": "-workbench.banner.focusPreviousAction",
        "when": "bannerFocused"
    },
    {
        "key": "ctrl+k",
        "command": "workbench.action.interactivePlayground.arrowUp",
        "when": "interactivePlaygroundFocus && !editorTextFocus"
    },
    {
        "key": "up",
        "command": "-workbench.action.interactivePlayground.arrowUp",
        "when": "interactivePlaygroundFocus && !editorTextFocus"
    },
    {
        "key": "ctrl+k",
        "command": "showPrevParameterHint",
        "when": "editorFocus && parameterHintsMultipleSignatures && parameterHintsVisible"
    },
    {
        "key": "up",
        "command": "-showPrevParameterHint",
        "when": "editorFocus && parameterHintsMultipleSignatures && parameterHintsVisible"
    },
    {
        "key": "ctrl+k",
        "command": "selectPrevCodeAction",
        "when": "codeActionMenuVisible"
    },
    {
        "key": "up",
        "command": "-selectPrevCodeAction",
        "when": "codeActionMenuVisible"
    },
    {
        "key": "ctrl+k",
        "command": "scm.viewPreviousCommit",
        "when": "scmInputIsInFirstPosition && scmRepository && !suggestWidgetVisible"
    },
    {
        "key": "up",
        "command": "-scm.viewPreviousCommit",
        "when": "scmInputIsInFirstPosition && scmRepository && !suggestWidgetVisible"
    },
    {
        "key": "ctrl+k",
        "command": "notifications.focusPreviousToast",
        "when": "notificationFocus && notificationToastsVisible"
    },
    {
        "key": "up",
        "command": "-notifications.focusPreviousToast",
        "when": "notificationFocus && notificationToastsVisible"
    },
    {
        "key": "ctrl+k",
        "command": "list.focusUp",
        "when": "listFocus && !inputFocus"
    },
    {
        "key": "up",
        "command": "-list.focusUp",
        "when": "listFocus && !inputFocus"
    },
    {
        "key": "ctrl+k",
        "command": "interactive.history.previous",
        "when": "!suggestWidgetVisible && resourceScheme == 'vscode-interactive' && interactiveInputCursorAtBoundary != 'bottom' && interactiveInputCursorAtBoundary != 'none'"
    },
    {
        "key": "up",
        "command": "-interactive.history.previous",
        "when": "!suggestWidgetVisible && resourceScheme == 'vscode-interactive' && interactiveInputCursorAtBoundary != 'bottom' && interactiveInputCursorAtBoundary != 'none'"
    },
    {
        "key": "ctrl+k",
        "command": "history.showPrevious",
        "when": "historyNavigationBackwardsEnabled && historyNavigationWidgetFocus && !suggestWidgetVisible"
    },
    {
        "key": "up",
        "command": "-history.showPrevious",
        "when": "historyNavigationBackwardsEnabled && historyNavigationWidgetFocus && !suggestWidgetVisible"
    },
    {
        "key": "up",
        "command": "cursorUp",
        "when": "textInputFocus"
    },
    {
        "key": "up",
        "command": "-cursorUp",
        "when": "textInputFocus"
    },
    {
        "key": "ctrl+k",
        "command": "workbench.action.terminal.navigationModeFocusPrevious",
        "when": "accessibilityModeEnabled && terminalA11yTreeFocus && terminalNavigationModeActive && terminalProcessSupported || accessibilityModeEnabled && terminalFocus && terminalNavigationModeActive && terminalProcessSupported"
    },
    {
        "key": "up",
        "command": "-workbench.action.terminal.navigationModeFocusPrevious",
        "when": "accessibilityModeEnabled && terminalA11yTreeFocus && terminalNavigationModeActive && terminalProcessSupported || accessibilityModeEnabled && terminalFocus && terminalNavigationModeActive && terminalProcessSupported"
    },
    {
        "key": "ctrl+k",
        "command": "notebook.focusPreviousEditor",
        "when": "config.notebook.navigation.allowNavigateToSurroundingCells && notebookCursorNavigationMode && notebookEditorFocused && !notebookCellMarkdownEditMode && notebookCellType == 'markup'"
    },
    {
        "key": "up",
        "command": "-notebook.focusPreviousEditor",
        "when": "config.notebook.navigation.allowNavigateToSurroundingCells && notebookCursorNavigationMode && notebookEditorFocused && !notebookCellMarkdownEditMode && notebookCellType == 'markup'"
    },
    {
        "key": "ctrl+k",
        "command": "notebook.focusPreviousEditor",
        "when": "config.notebook.navigation.allowNavigateToSurroundingCells && editorTextFocus && inputFocus && notebookEditorFocused && notebookEditorCursorAtBoundary != 'bottom' && notebookEditorCursorAtBoundary != 'none'"
    },
    {
        "key": "up",
        "command": "-notebook.focusPreviousEditor",
        "when": "config.notebook.navigation.allowNavigateToSurroundingCells && editorTextFocus && inputFocus && notebookEditorFocused && notebookEditorCursorAtBoundary != 'bottom' && notebookEditorCursorAtBoundary != 'none'"
    },
    {
        "key": "ctrl+cmd+l",
        "command": "workbench.action.moveEditorToNextGroup"
    },
    {
        "key": "ctrl+cmd+right",
        "command": "-workbench.action.moveEditorToNextGroup"
    },
    {
        "key": "ctrl+cmd+h",
        "command": "workbench.action.moveEditorToPreviousGroup"
    },
    {
        "key": "ctrl+cmd+left",
        "command": "-workbench.action.moveEditorToPreviousGroup"
    }
]